picopt/__init__.py
picopt/archiveinfo.py
picopt/cli.py
picopt/config/__init__.py
picopt/config/consts.py
picopt/config/cwebp.py
picopt/config/handlers.py
picopt/config_default.yaml
picopt/exceptions.py
picopt/formats.py
picopt/handlers/__init__.py
picopt/handlers/container/__init__.py
picopt/handlers/container/animated/__init__.py
picopt/handlers/container/animated/img2webp.py
picopt/handlers/container/animated/webp.py
picopt/handlers/container/animated/webpbase.py
picopt/handlers/container/animated/webpmux.py
picopt/handlers/container/archive/__init__.py
picopt/handlers/container/archive/rar.py
picopt/handlers/container/archive/seven_zip.py
picopt/handlers/container/archive/tar.py
picopt/handlers/container/archive/zip.py
picopt/handlers/handler/__init__.py
picopt/handlers/handler/cleanup.py
picopt/handlers/handler/init.py
picopt/handlers/image/__init__.py
picopt/handlers/image/gif.py
picopt/handlers/image/jpeg.py
picopt/handlers/image/png.py
picopt/handlers/image/svg.py
picopt/handlers/image/webp.py
picopt/handlers/mixins.py
picopt/old_timestamps.py
picopt/path.py
picopt/pillow/__init__.py
picopt/pillow/header.py
picopt/pillow/jpeg_xmp.py
picopt/pillow/png_bit_depth.py
picopt/pillow/webp_lossless.py
picopt/printer.py
picopt/report.py
picopt/walk/__init__.py
picopt/walk/detect_format.py
picopt/walk/handler_factory.py
picopt/walk/init.py
picopt/walk/skip.py
picopt/walk/walk.py
picopt-5.3.1.dist-info/WHEEL
picopt-5.3.1.dist-info/entry_points.txt
picopt-5.3.1.dist-info/METADATA
picopt-5.3.1.dist-info/RECORD
