Metadata-Version: 2.3
Name: picopt
Version: 5.3.1
Summary: A multi format lossless image optimizer that uses external tools
Keywords: image,png,jpg,cbz,cbr
Author: AJ Slater
Author-email: AJ Slater <aj@slater.net>
License: GPL-3.0-only
Classifier: Topic :: Internet :: WWW/HTTP :: Site Management
Classifier: Topic :: Multimedia :: Graphics :: Graphics Conversion
Classifier: Operating System :: OS Independent
Classifier: Development Status :: 5 - Production/Stable
Classifier: Intended Audience :: Developers
Classifier: Intended Audience :: System Administrators
Classifier: Environment :: Console
Classifier: Programming Language :: Python :: 3 :: Only
Classifier: Typing :: Typed
Requires-Dist: confuse>=2.1.0,<2.2.0
Requires-Dist: defusedxml>=0.7,<1.0
Requires-Dist: filetype~=1.2
Requires-Dist: humanize~=4.12
Requires-Dist: mozjpeg-lossless-optimization~=1.3
Requires-Dist: piexif~=1.1
Requires-Dist: py7zr~=1.0
Requires-Dist: pyoxipng~=9.1
Requires-Dist: python-dateutil~=2.8
Requires-Dist: rarfile~=4.0
Requires-Dist: ruamel-yaml>=0.18,<1.0
Requires-Dist: treestamps~=2.2
Requires-Dist: typing-extensions~=4.13
Requires-Dist: pillow>=12.0
Requires-Python: >=3.10
Project-URL: Documentation, https://picopt.readthedocs.io
Project-URL: Issues, https://github.com/ajslater/picopt/issues
Project-URL: News, https://picopt.readthedocs.io/news/
Project-URL: Source, https://github.com/ajslater/picopt
